akismet-25.10.1.dist-info/METADATA
akismet-25.10.1.dist-info/WHEEL
akismet-25.10.1.dist-info/entry_points.txt
akismet-25.10.1.dist-info/licenses/LICENSE
akismet/__init__.py
akismet/_async_client.py
akismet/_common.py
akismet/_exceptions.py
akismet/_sync_client.py
akismet/_test_clients.py
akismet/py.typed
akismet/pytest_plugin.py
akismet-25.10.1.dist-info/RECORD
