Metadata-Version: 2.1
Name: akismet
Version: 25.10.1
Summary: A Python interface to the Akismet spam-filtering service.
Keywords: akismet,spam,spam-filtering
Author: Michael Foord, James Bennett
Maintainer: James Bennett
License: BSD-3-Clause
Classifier: Development Status :: 5 - Production/Stable
Classifier: Environment :: Web Environment
Classifier: Intended Audience :: Developers
Classifier: License :: OSI Approved :: BSD License
Classifier: Operating System :: OS Independent
Classifier: Programming Language :: Python
Classifier: Programming Language :: Python :: 3
Classifier: Programming Language :: Python :: 3.10
Classifier: Programming Language :: Python :: 3.11
Classifier: Programming Language :: Python :: 3.12
Classifier: Programming Language :: Python :: 3.13
Classifier: Programming Language :: Python :: 3.14
Classifier: Topic :: Utilities
Classifier: Typing :: Typed
Project-URL: Documentation, https://akismet.readthedocs.io
Project-URL: Source Code, https://github.com/ubernostrum/akismet
Requires-Python: >=3.10
Requires-Dist: httpx
Requires-Dist: typing-extensions
